bacon_replay_analyzer/__init__.py
bacon_replay_analyzer/bco_repo.py
bacon_replay_analyzer/var/bco-analyzer/bco_repo.json
bacon_replay_analyzer-0.0.9.dist-info/AUTHORS
bacon_replay_analyzer-0.0.9.dist-info/METADATA
bacon_replay_analyzer-0.0.9.dist-info/WHEEL
bacon_replay_analyzer-0.0.9.dist-info/pbr.json
bacon_replay_analyzer-0.0.9.dist-info/top_level.txt
bacon_replay_analyzer-0.0.9.dist-info/RECORD
