Metadata-Version: 2.1
Name: bacon-replay-analyzer
Version: 0.0.9
Summary: UNKNOWN
Home-page: UNKNOWN
Author: Calen Pennington
Author-email: calen.pennington@gmail.com
License: UNKNOWN
Platform: UNKNOWN
Requires-Dist: attrs (==19.1.0)
